simo_heos/__init__.py
simo_heos/apps.py
simo_heos/controllers.py
simo_heos/forms.py
simo_heos/gateways.py
simo_heos/models.py
simo_heos/on_start.py
simo_heos/transport.py
simo_heos/utils.py
simo_heos/__pycache__/__init__.cpython-312.pyc
simo_heos/__pycache__/__init__.cpython-38.pyc
simo_heos/__pycache__/apps.cpython-312.pyc
simo_heos/__pycache__/apps.cpython-38.pyc
simo_heos/__pycache__/controllers.cpython-312.pyc
simo_heos/__pycache__/controllers.cpython-38.pyc
simo_heos/__pycache__/forms.cpython-312.pyc
simo_heos/__pycache__/forms.cpython-38.pyc
simo_heos/__pycache__/gateways.cpython-312.pyc
simo_heos/__pycache__/gateways.cpython-38.pyc
simo_heos/__pycache__/models.cpython-312.pyc
simo_heos/__pycache__/models.cpython-38.pyc
simo_heos/__pycache__/on_start.cpython-38.pyc
simo_heos/__pycache__/transport.cpython-312.pyc
simo_heos/__pycache__/transport.cpython-38.pyc
simo_heos/__pycache__/utils.cpython-312.pyc
simo_heos/__pycache__/utils.cpython-38.pyc
simo_heos/migrations/0001_initial.py
simo_heos/migrations/0002_alter_hplayer_pid_alter_hplayer_unique_together.py
simo_heos/migrations/__init__.py
simo_heos/migrations/__pycache__/0001_initial.cpython-312.pyc
simo_heos/migrations/__pycache__/0001_initial.cpython-38.pyc
simo_heos/migrations/__pycache__/0002_alter_hplayer_pid_alter_hplayer_unique_together.cpython-312.pyc
simo_heos/migrations/__pycache__/__init__.cpython-312.pyc
simo_heos/migrations/__pycache__/__init__.cpython-38.pyc
simo_heos-1.0.8.dist-info/licenses/LICENSE.md
simo_heos-1.0.8.dist-info/METADATA
simo_heos-1.0.8.dist-info/WHEEL
simo_heos-1.0.8.dist-info/top_level.txt
simo_heos-1.0.8.dist-info/RECORD
