Metadata-Version: 2.4
Name: simo-heos
Version: 1.0.8
Summary: DENON HEOS integration for SIMO.io
Author-email: "Simon V." <simon@simo.io>
Project-URL: Homepage, https://github.com/SIMO-io/simo-heos
Project-URL: Issues, https://github.com/SIMO-io/simo-heos/issues
Classifier: Programming Language :: Python :: 3
Classifier: License :: OSI Approved :: MIT License
Classifier: Operating System :: OS Independent
Requires-Python: >=3.8
License-File: LICENSE.md
Requires-Dist: simo>=2.7.6
Dynamic: license-file
